README.md
setup.py
kha/__init__.py
kha/cli.py
kha/const.py
kha/scripts/__init__.py
kha/scripts/ssh.py
kha/scripts/translate.py
kha/scripts/ts.py
kha/utils/__init__.py
kha/utils/file_utils.py
kha_cli.egg-info/PKG-INFO
kha_cli.egg-info/SOURCES.txt
kha_cli.egg-info/dependency_links.txt
kha_cli.egg-info/entry_points.txt
kha_cli.egg-info/not-zip-safe
kha_cli.egg-info/requires.txt
kha_cli.egg-info/top_level.txt