Metadata-Version: 2.1
Name: kha-cli
Version: 1.1.2
Summary: kha
Author: khahux
Author-email: khahux@gmail.com
Requires-Python: >=3.8
